{
    "name": "chunk 3 , 9",
    "chunkMesh": {
        "instanceID": -581876
    },
    "material": {
        "instanceID": -581878
    },
    "position": {
        "x": 192.0,
        "y": 0.0,
        "z": 576.0
    },
    "objectNames": [
        "Tree2(Clone)"
    ],
    "objects": [
        {
            "instanceID": -581890
        }
    ],
    "objectMeshes": [
        {
            "instanceID": 23542
        }
    ],
    "objectVertices": [],
    "objectTriangles": [],
    "objectUvs": [],
    "objectTextures": [],
    "objectMaterials": [
        {
            "instanceID": -581898
        }
    ],
    "objectPos": [
        {
            "x": 220.36390686035157,
            "y": 41.960784912109378,
            "z": 633.02734375
        }
    ],
    "objectRot": [],
    "spawnerScriptableObject": {
        "instanceID": 0
    },
    "treeLODMeshes": [
        {
            "instanceID": 23538
        },
        {
            "instanceID": 23540
        },
        {
            "instanceID": 23542
        }
    ]
}