{
    "name": "chunk 1 , 7",
    "chunkMesh": {
        "instanceID": -301066
    },
    "material": {
        "instanceID": -301068
    },
    "position": {
        "x": 64.0,
        "y": 0.0,
        "z": 448.0
    },
    "objectNames": [
        "Tree2(Clone)"
    ],
    "objects": [
        {
            "instanceID": -301080
        }
    ],
    "objectMeshes": [
        {
            "instanceID": 23776
        }
    ],
    "objectVertices": [],
    "objectTriangles": [],
    "objectUvs": [],
    "objectTextures": [],
    "objectMaterials": [
        {
            "instanceID": -301088
        }
    ],
    "objectPos": [
        {
            "x": 107.05380249023438,
            "y": 56.015140533447269,
            "z": 471.9575500488281
        }
    ],
    "spawnerScriptableObject": {
        "instanceID": 0
    },
    "treeLODMeshes": [
        {
            "instanceID": 23772
        },
        {
            "instanceID": 23774
        },
        {
            "instanceID": 23776
        }
    ]
}