{
    "name": "chunk 0 , 8",
    "chunkMesh": {
        "instanceID": -6074
    },
    "material": {
        "instanceID": -6076
    },
    "position": {
        "x": 0.0,
        "y": 0.0,
        "z": 512.0
    },
    "objectNames": [],
    "objects": [],
    "objectMeshes": [],
    "objectMaterials": [],
    "objectPos": [],
    "treeLODMeshes": [
        {
            "instanceID": 0
        },
        {
            "instanceID": 0
        },
        {
            "instanceID": 0
        }
    ]
}