{
    "name": "chunk 5 , 10",
    "chunkMesh": {
        "instanceID": -11974
    },
    "material": {
        "instanceID": -11976
    },
    "position": {
        "x": 320.0,
        "y": 0.0,
        "z": 640.0
    },
    "objectNames": [],
    "objects": [],
    "objectMeshes": [],
    "objectMaterials": [],
    "objectPos": [],
    "spawnerPrefab": {
        "instanceID": 0
    },
    "treeLODMeshes": [
        {
            "instanceID": 0
        },
        {
            "instanceID": 0
        },
        {
            "instanceID": 0
        }
    ]
}